pyCatSim/__init__.py
pycatsim-2025.7.11.dist-info/METADATA
pycatsim-2025.7.11.dist-info/WHEEL
pycatsim-2025.7.11.dist-info/top_level.txt
pycatsim-2025.7.11.dist-info/RECORD
