Metadata-Version: 2.4
Name: pyCatSim
Version: 2025.7.11
Summary: A fun, modular, object-oriented Python package for simulating cat behavior
Author-email: Deborah Khider <khider@usc.edu>
License: Apache-2.0
Project-URL: Homepage, https://github.com/khider/pyCatSim
Project-URL: Issues, https://github.com/khider/pyCatSim/issues
Requires-Python: >=3.12
Requires-Dist: playsound>=1.3.0
Requires-Dist: matplotlib
